{
  "runs": [
    {
      "result_json": "toy_quantvla/results/phase16_step253_focused_replay_v1_action_head_model.json",
      "target": "action_head_model",
      "case_list": "6:8",
      "focus_policy_steps": [
        248,
        249,
        250,
        251,
        252,
        253,
        254,
        255,
        256,
        257,
        258
      ],
      "seed_offsets": [
        -2,
        -1,
        0,
        1,
        2
      ],
      "repeats": 3,
      "step_rows": 11,
      "top_step": {
        "target": "action_head_model",
        "case": "task6:init8",
        "policy_step": 253,
        "samples": 15,
        "continuous_max_abs_max": 0.054931640625,
        "continuous_max_abs_p99": 0.054931640625,
        "continuous_l2_p99": 0.0773857710423978,
        "same_seed_repeat_span_max": 0.0,
        "top_dim": "x",
        "top_seed_offset": 0,
        "top_repeat": 0,
        "raw_diff": {
          "x": 0.054931640625,
          "y": -0.0059223175048828125,
          "z": 0.0423431396484375,
          "roll": -0.0034050792455673218,
          "pitch": 0.03363123536109924,
          "yaw": -0.0006344616413116455,
          "gripper": -0.001953125
        },
        "compiled_p50_seconds": 0.06131293997168541,
        "eager_p50_seconds": 0.150845255702734,
        "time_ratio_p50": 0.40874540283501604
      },
      "compiled_p50_mean_seconds": 0.062399321659044785,
      "eager_p50_mean_seconds": 0.14294856617396529
    },
    {
      "result_json": "toy_quantvla/results/phase16_step253_focused_replay_v1_action_head_model_blocks_8_15_eager.json",
      "target": "action_head_model_blocks_8_15_eager",
      "case_list": "6:8",
      "focus_policy_steps": [
        248,
        249,
        250,
        251,
        252,
        253,
        254,
        255,
        256,
        257,
        258
      ],
      "seed_offsets": [
        -2,
        -1,
        0,
        1,
        2
      ],
      "repeats": 3,
      "step_rows": 11,
      "top_step": {
        "target": "action_head_model_blocks_8_15_eager",
        "case": "task6:init8",
        "policy_step": 253,
        "samples": 15,
        "continuous_max_abs_max": 0.054931640625,
        "continuous_max_abs_p99": 0.054931640625,
        "continuous_l2_p99": 0.0757392833263687,
        "same_seed_repeat_span_max": 0.0,
        "top_dim": "x",
        "top_seed_offset": 0,
        "top_repeat": 0,
        "raw_diff": {
          "x": 0.054931640625,
          "y": -0.0068950653076171875,
          "z": 0.0391387939453125,
          "roll": -0.0028812140226364136,
          "pitch": 0.03363123536109924,
          "yaw": -0.0004532039165496826,
          "gripper": -0.00146484375
        },
        "compiled_p50_seconds": 0.07809189707040787,
        "eager_p50_seconds": 0.11025772616267204,
        "time_ratio_p50": 0.7228762269095625
      },
      "compiled_p50_mean_seconds": 0.08349292996254834,
      "eager_p50_mean_seconds": 0.11703084409236908
    },
    {
      "result_json": "toy_quantvla/results/phase16_step253_focused_replay_v1_action_head_dit_attn_all.json",
      "target": "action_head_dit_attn_all",
      "case_list": "6:8",
      "focus_policy_steps": [
        248,
        249,
        250,
        251,
        252,
        253,
        254,
        255,
        256,
        257,
        258
      ],
      "seed_offsets": [
        -2,
        -1,
        0,
        1,
        2
      ],
      "repeats": 3,
      "step_rows": 11,
      "top_step": {
        "target": "action_head_dit_attn_all",
        "case": "task6:init8",
        "policy_step": 258,
        "samples": 15,
        "continuous_max_abs_max": 0.0019598007202148438,
        "continuous_max_abs_p99": 0.0019598007202148438,
        "continuous_l2_p99": 0.0029791698494895467,
        "same_seed_repeat_span_max": 0.0,
        "top_dim": "x",
        "top_seed_offset": 1,
        "top_repeat": 0,
        "raw_diff": {
          "x": -0.0019598007202148438,
          "y": 0.00091552734375,
          "z": -0.0018310546875,
          "roll": 0.0,
          "pitch": -0.0008773505687713623,
          "yaw": 0.00027191638946533203,
          "gripper": -0.0001220703125
        },
        "compiled_p50_seconds": 0.10403793305158615,
        "eager_p50_seconds": 0.10676223412156105,
        "time_ratio_p50": 0.9744825397071312
      },
      "compiled_p50_mean_seconds": 0.10296459800817749,
      "eager_p50_mean_seconds": 0.10754224082285707
    }
  ],
  "step_rows": [
    {
      "target": "action_head_model",
      "case": "task6:init8",
      "policy_step": 248,
      "samples": 15,
      "continuous_max_abs_max": 0.00274658203125,
      "continuous_max_abs_p99": 0.00274658203125,
      "continuous_l2_p99": 0.003576054287988152,
      "same_seed_repeat_span_max": 0.0,
      "top_dim": "z",
      "top_seed_offset": -2,
      "top_repeat": 0,
      "raw_diff": {
        "x": 0.0012874603271484375,
        "y": 0.0018310546875,
        "z": -0.00274658203125,
        "roll": 0.0001309514045715332,
        "pitch": 0.0002924501895904541,
        "yaw": 0.00036257505416870117,
        "gripper": -0.001220703125
      },
      "compiled_p50_seconds": 0.062441978603601456,
      "eager_p50_seconds": 0.1422279141843319,
      "time_ratio_p50": 0.4403097136330474
    },
    {
      "target": "action_head_model",
      "case": "task6:init8",
      "policy_step": 249,
      "samples": 15,
      "continuous_max_abs_max": 0.0020885467529296875,
      "continuous_max_abs_p99": 0.0020885467529296875,
      "continuous_l2_p99": 0.0027825225586234287,
      "same_seed_repeat_span_max": 0.0,
      "top_dim": "z",
      "top_seed_offset": 2,
      "top_repeat": 0,
      "raw_diff": {
        "x": -0.0017005205154418945,
        "y": -0.0006866455078125,
        "z": -0.0020885467529296875,
        "roll": -0.00013096630573272705,
        "pitch": 0.0,
        "yaw": 0.0,
        "gripper": 0.000732421875
      },
      "compiled_p50_seconds": 0.06370740011334419,
      "eager_p50_seconds": 0.14486387372016907,
      "time_ratio_p50": 0.40875279194492264
    },
    {
      "target": "action_head_model",
      "case": "task6:init8",
      "policy_step": 250,
      "samples": 15,
      "continuous_max_abs_max": 0.001373291015625,
      "continuous_max_abs_p99": 0.001373291015625,
      "continuous_l2_p99": 0.0013852012764873657,
      "same_seed_repeat_span_max": 0.0,
      "top_dim": "y",
      "top_seed_offset": -1,
      "top_repeat": 0,
      "raw_diff": {
        "x": 0.0,
        "y": -0.001373291015625,
        "z": 0.0,
        "roll": 0.0,
        "pitch": 0.0,
        "yaw": 0.0001812577247619629,
        "gripper": -0.0009765625
      },
      "compiled_p50_seconds": 0.06210271641612053,
      "eager_p50_seconds": 0.14156843721866608,
      "time_ratio_p50": 0.4400215246828047
    },
    {
      "target": "action_head_model",
      "case": "task6:init8",
      "policy_step": 251,
      "samples": 15,
      "continuous_max_abs_max": 0.001373291015625,
      "continuous_max_abs_p99": 0.001373291015625,
      "continuous_l2_p99": 0.0021129138119022816,
      "same_seed_repeat_span_max": 0.0,
      "top_dim": "x",
      "top_seed_offset": 2,
      "top_repeat": 0,
      "raw_diff": {
        "x": 0.001373291015625,
        "y": 0.00102996826171875,
        "z": 0.00057220458984375,
        "roll": -0.0002619326114654541,
        "pitch": 0.0010235607624053955,
        "yaw": 0.00027191638946533203,
        "gripper": -0.001953125
      },
      "compiled_p50_seconds": 0.06313642859458923,
      "eager_p50_seconds": 0.14255398139357567,
      "time_ratio_p50": 0.4470077253337013
    },
    {
      "target": "action_head_model",
      "case": "task6:init8",
      "policy_step": 252,
      "samples": 15,
      "continuous_max_abs_max": 0.0016021728515625,
      "continuous_max_abs_p99": 0.0016021728515625,
      "continuous_l2_p99": 0.0017256378230413542,
      "same_seed_repeat_span_max": 0.0,
      "top_dim": "z",
      "top_seed_offset": 1,
      "top_repeat": 0,
      "raw_diff": {
        "x": 0.0,
        "y": 5.7220458984375e-05,
        "z": -0.0016021728515625,
        "roll": 0.0,
        "pitch": 0.0,
        "yaw": 0.0,
        "gripper": -0.001953125
      },
      "compiled_p50_seconds": 0.0633813738822937,
      "eager_p50_seconds": 0.14266009628772736,
      "time_ratio_p50": 0.44437703083041363
    },
    {
      "target": "action_head_model",
      "case": "task6:init8",
      "policy_step": 253,
      "samples": 15,
      "continuous_max_abs_max": 0.054931640625,
      "continuous_max_abs_p99": 0.054931640625,
      "continuous_l2_p99": 0.0773857710423978,
      "same_seed_repeat_span_max": 0.0,
      "top_dim": "x",
      "top_seed_offset": 0,
      "top_repeat": 0,
      "raw_diff": {
        "x": 0.054931640625,
        "y": -0.0059223175048828125,
        "z": 0.0423431396484375,
        "roll": -0.0034050792455673218,
        "pitch": 0.03363123536109924,
        "yaw": -0.0006344616413116455,
        "gripper": -0.001953125
      },
      "compiled_p50_seconds": 0.06131293997168541,
      "eager_p50_seconds": 0.150845255702734,
      "time_ratio_p50": 0.40874540283501604
    },
    {
      "target": "action_head_model",
      "case": "task6:init8",
      "policy_step": 254,
      "samples": 15,
      "continuous_max_abs_max": 0.001373291015625,
      "continuous_max_abs_p99": 0.001373291015625,
      "continuous_l2_p99": 0.0016899025771755921,
      "same_seed_repeat_span_max": 0.0,
      "top_dim": "y",
      "top_seed_offset": -2,
      "top_repeat": 0,
      "raw_diff": {
        "x": -0.00091552734375,
        "y": 0.001373291015625,
        "z": 0.0,
        "roll": -9.822845458984375e-05,
        "pitch": 0.0001462101936340332,
        "yaw": 0.0003172159194946289,
        "gripper": 0.0
      },
      "compiled_p50_seconds": 0.06154857203364372,
      "eager_p50_seconds": 0.1412883810698986,
      "time_ratio_p50": 0.4364923447731482
    },
    {
      "target": "action_head_model",
      "case": "task6:init8",
      "policy_step": 255,
      "samples": 15,
      "continuous_max_abs_max": 0.00091552734375,
      "continuous_max_abs_p99": 0.00091552734375,
      "continuous_l2_p99": 0.0012005045935802438,
      "same_seed_repeat_span_max": 0.0,
      "top_dim": "x",
      "top_seed_offset": -2,
      "top_repeat": 0,
      "raw_diff": {
        "x": 0.00091552734375,
        "y": -0.00011444091796875,
        "z": -0.0002288818359375,
        "roll": 0.0,
        "pitch": 0.0,
        "yaw": 0.0,
        "gripper": -0.0008544921875
      },
      "compiled_p50_seconds": 0.061616603285074234,
      "eager_p50_seconds": 0.14104729518294334,
      "time_ratio_p50": 0.4375195362478828
    },
    {
      "target": "action_head_model",
      "case": "task6:init8",
      "policy_step": 256,
      "samples": 15,
      "continuous_max_abs_max": 0.001373291015625,
      "continuous_max_abs_p99": 0.001373291015625,
      "continuous_l2_p99": 0.0016491764739825613,
      "same_seed_repeat_span_max": 0.0,
      "top_dim": "x",
      "top_seed_offset": 1,
      "top_repeat": 0,
      "raw_diff": {
        "x": -0.001373291015625,
        "y": -0.000457763671875,
        "z": -0.0006866455078125,
        "roll": 0.0,
        "pitch": 0.0001462399959564209,
        "yaw": -0.0003625452518463135,
        "gripper": -0.0019530951976776123
      },
      "compiled_p50_seconds": 0.06162261590361595,
      "eager_p50_seconds": 0.14077257737517357,
      "time_ratio_p50": 0.4589487544118784
    },
    {
      "target": "action_head_model",
      "case": "task6:init8",
      "policy_step": 257,
      "samples": 15,
      "continuous_max_abs_max": 0.00274658203125,
      "continuous_max_abs_p99": 0.00274658203125,
      "continuous_l2_p99": 0.0028875559163788122,
      "same_seed_repeat_span_max": 0.0,
      "top_dim": "z",
      "top_seed_offset": 2,
      "top_repeat": 0,
      "raw_diff": {
        "x": 0.000400543212890625,
        "y": 0.0006866455078125,
        "z": 0.00274658203125,
        "roll": -0.0002619326114654541,
        "pitch": -0.0002924501895904541,
        "yaw": -9.062886238098145e-05,
        "gripper": 0.000244140625
      },
      "compiled_p50_seconds": 0.06197220832109451,
      "eager_p50_seconds": 0.14066902548074722,
      "time_ratio_p50": 0.43718537656088596
    },
    {
      "target": "action_head_model",
      "case": "task6:init8",
      "policy_step": 258,
      "samples": 15,
      "continuous_max_abs_max": 0.004248619079589844,
      "continuous_max_abs_p99": 0.004248619079589844,
      "continuous_l2_p99": 0.0062453616243256195,
      "same_seed_repeat_span_max": 0.0,
      "top_dim": "x",
      "top_seed_offset": 1,
      "top_repeat": 0,
      "raw_diff": {
        "x": 0.004248619079589844,
        "y": -0.00091552734375,
        "z": 0.0018310546875,
        "roll": 0.0,
        "pitch": 0.004094243049621582,
        "yaw": 0.0,
        "gripper": 0.000732421875
      },
      "compiled_p50_seconds": 0.0635497011244297,
      "eager_p50_seconds": 0.1439373902976513,
      "time_ratio_p50": 0.44203937154268846
    },
    {
      "target": "action_head_model_blocks_8_15_eager",
      "case": "task6:init8",
      "policy_step": 248,
      "samples": 15,
      "continuous_max_abs_max": 0.00457763671875,
      "continuous_max_abs_p99": 0.00457763671875,
      "continuous_l2_p99": 0.004952579568783357,
      "same_seed_repeat_span_max": 0.0,
      "top_dim": "z",
      "top_seed_offset": -2,
      "top_repeat": 0,
      "raw_diff": {
        "x": 0.0001430511474609375,
        "y": 0.0018310546875,
        "z": -0.00457763671875,
        "roll": 0.00026191771030426025,
        "pitch": 0.0,
        "yaw": 0.00036257505416870117,
        "gripper": -0.0009765625
      },
      "compiled_p50_seconds": 0.08494171127676964,
      "eager_p50_seconds": 0.12231570482254028,
      "time_ratio_p50": 0.6713750311000917
    },
    {
      "target": "action_head_model_blocks_8_15_eager",
      "case": "task6:init8",
      "policy_step": 249,
      "samples": 15,
      "continuous_max_abs_max": 0.0018596649169921875,
      "continuous_max_abs_p99": 0.0018596649169921875,
      "continuous_l2_p99": 0.001980034720566912,
      "same_seed_repeat_span_max": 0.0,
      "top_dim": "z",
      "top_seed_offset": 2,
      "top_repeat": 0,
      "raw_diff": {
        "x": -0.0006401538848876953,
        "y": 0.0002288818359375,
        "z": -0.0018596649169921875,
        "roll": 0.0,
        "pitch": 0.0,
        "yaw": 0.0,
        "gripper": 0.000732421875
      },
      "compiled_p50_seconds": 0.08468513190746307,
      "eager_p50_seconds": 0.12623192742466927,
      "time_ratio_p50": 0.6578220269801192
    },
    {
      "target": "action_head_model_blocks_8_15_eager",
      "case": "task6:init8",
      "policy_step": 250,
      "samples": 15,
      "continuous_max_abs_max": 0.0018310546875,
      "continuous_max_abs_p99": 0.0018310546875,
      "continuous_l2_p99": 0.002086536469756626,
      "same_seed_repeat_span_max": 0.0,
      "top_dim": "z",
      "top_seed_offset": -2,
      "top_repeat": 0,
      "raw_diff": {
        "x": -0.00091552734375,
        "y": 0.00011444091796875,
        "z": -0.0018310546875,
        "roll": -0.0002619326114654541,
        "pitch": -0.0002193450927734375,
        "yaw": -0.00018128752708435059,
        "gripper": -0.000244140625
      },
      "compiled_p50_seconds": 0.09059927985072136,
      "eager_p50_seconds": 0.12020404264330864,
      "time_ratio_p50": 0.7053334106760851
    },
    {
      "target": "action_head_model_blocks_8_15_eager",
      "case": "task6:init8",
      "policy_step": 251,
      "samples": 15,
      "continuous_max_abs_max": 0.001373291015625,
      "continuous_max_abs_p99": 0.001373291015625,
      "continuous_l2_p99": 0.0021123426309649414,
      "same_seed_repeat_span_max": 0.0,
      "top_dim": "x",
      "top_seed_offset": 2,
      "top_repeat": 0,
      "raw_diff": {
        "x": 0.001373291015625,
        "y": 0.00102996826171875,
        "z": 0.0006866455078125,
        "roll": -0.0002619326114654541,
        "pitch": 0.0008773505687713623,
        "yaw": 0.0004532039165496826,
        "gripper": -0.00244140625
      },
      "compiled_p50_seconds": 0.08472101390361786,
      "eager_p50_seconds": 0.12113276869058609,
      "time_ratio_p50": 0.7054934097900125
    },
    {
      "target": "action_head_model_blocks_8_15_eager",
      "case": "task6:init8",
      "policy_step": 252,
      "samples": 15,
      "continuous_max_abs_max": 0.0020599365234375,
      "continuous_max_abs_p99": 0.0020599365234375,
      "continuous_l2_p99": 0.002165940218463404,
      "same_seed_repeat_span_max": 0.0,
      "top_dim": "z",
      "top_seed_offset": 1,
      "top_repeat": 0,
      "raw_diff": {
        "x": 0.000457763671875,
        "y": 0.00011444091796875,
        "z": -0.0020599365234375,
        "roll": 0.0,
        "pitch": 0.000438690185546875,
        "yaw": 0.00018128752708435059,
        "gripper": -0.0009765625
      },
      "compiled_p50_seconds": 0.0901288315653801,
      "eager_p50_seconds": 0.12065912410616875,
      "time_ratio_p50": 0.7104700623197402
    },
    {
      "target": "action_head_model_blocks_8_15_eager",
      "case": "task6:init8",
      "policy_step": 253,
      "samples": 15,
      "continuous_max_abs_max": 0.054931640625,
      "continuous_max_abs_p99": 0.054931640625,
      "continuous_l2_p99": 0.0757392833263687,
      "same_seed_repeat_span_max": 0.0,
      "top_dim": "x",
      "top_seed_offset": 0,
      "top_repeat": 0,
      "raw_diff": {
        "x": 0.054931640625,
        "y": -0.0068950653076171875,
        "z": 0.0391387939453125,
        "roll": -0.0028812140226364136,
        "pitch": 0.03363123536109924,
        "yaw": -0.0004532039165496826,
        "gripper": -0.00146484375
      },
      "compiled_p50_seconds": 0.07809189707040787,
      "eager_p50_seconds": 0.11025772616267204,
      "time_ratio_p50": 0.7228762269095625
    },
    {
      "target": "action_head_model_blocks_8_15_eager",
      "case": "task6:init8",
      "policy_step": 254,
      "samples": 15,
      "continuous_max_abs_max": 0.001468062400817871,
      "continuous_max_abs_p99": 0.001468062400817871,
      "continuous_l2_p99": 0.0017819143700850298,
      "same_seed_repeat_span_max": 0.0,
      "top_dim": "x",
      "top_seed_offset": 0,
      "top_repeat": 0,
      "raw_diff": {
        "x": -0.001468062400817871,
        "y": 0.0006866455078125,
        "z": -0.00011444091796875,
        "roll": 6.549060344696045e-05,
        "pitch": -7.31050968170166e-05,
        "yaw": 0.0007251203060150146,
        "gripper": 0.000732421875
      },
      "compiled_p50_seconds": 0.07609744369983673,
      "eager_p50_seconds": 0.10097353532910347,
      "time_ratio_p50": 0.7627034374092482
    },
    {
      "target": "action_head_model_blocks_8_15_eager",
      "case": "task6:init8",
      "policy_step": 255,
      "samples": 15,
      "continuous_max_abs_max": 0.0009576082229614258,
      "continuous_max_abs_p99": 0.0009576082229614258,
      "continuous_l2_p99": 0.0014245105164301124,
      "same_seed_repeat_span_max": 0.0,
      "top_dim": "x",
      "top_seed_offset": -1,
      "top_repeat": 0,
      "raw_diff": {
        "x": -0.0009576082229614258,
        "y": 0.0002288818359375,
        "z": -0.00034332275390625,
        "roll": -0.00019644200801849365,
        "pitch": 0.0,
        "yaw": 0.0,
        "gripper": 0.000732421875
      },
      "compiled_p50_seconds": 0.07616376876831055,
      "eager_p50_seconds": 0.09653343632817268,
      "time_ratio_p50": 0.7870431583039198
    },
    {
      "target": "action_head_model_blocks_8_15_eager",
      "case": "task6:init8",
      "policy_step": 256,
      "samples": 15,
      "continuous_max_abs_max": 0.0017009377479553223,
      "continuous_max_abs_p99": 0.0017009377479553223,
      "continuous_l2_p99": 0.0019414317529650397,
      "same_seed_repeat_span_max": 0.0,
      "top_dim": "z",
      "top_seed_offset": -1,
      "top_repeat": 0,
      "raw_diff": {
        "x": 0.0,
        "y": 0.00091552734375,
        "z": -0.0017009377479553223,
        "roll": 0.00018008053302764893,
        "pitch": 7.31348991394043e-05,
        "yaw": 0.0,
        "gripper": 0.0
      },
      "compiled_p50_seconds": 0.08437757566571236,
      "eager_p50_seconds": 0.11786211654543877,
      "time_ratio_p50": 0.7086023414798184
    },
    {
      "target": "action_head_model_blocks_8_15_eager",
      "case": "task6:init8",
      "policy_step": 257,
      "samples": 15,
      "continuous_max_abs_max": 0.0018310546875,
      "continuous_max_abs_p99": 0.0018310546875,
      "continuous_l2_p99": 0.002108137547375737,
      "same_seed_repeat_span_max": 0.0,
      "top_dim": "z",
      "top_seed_offset": 2,
      "top_repeat": 0,
      "raw_diff": {
        "x": 0.0002574920654296875,
        "y": 0.00091552734375,
        "z": 0.0018310546875,
        "roll": -0.0002619326114654541,
        "pitch": -0.0002924501895904541,
        "yaw": -0.0001812577247619629,
        "gripper": 0.000732421875
      },
      "compiled_p50_seconds": 0.08364356309175491,
      "eager_p50_seconds": 0.1252339631319046,
      "time_ratio_p50": 0.6723759113568982
    },
    {
      "target": "action_head_model_blocks_8_15_eager",
      "case": "task6:init8",
      "policy_step": 258,
      "samples": 15,
      "continuous_max_abs_max": 0.0039052963256835938,
      "continuous_max_abs_p99": 0.0039052963256835938,
      "continuous_l2_p99": 0.005238590768313196,
      "same_seed_repeat_span_max": 0.0,
      "top_dim": "x",
      "top_seed_offset": 1,
      "top_repeat": 0,
      "raw_diff": {
        "x": 0.0039052963256835938,
        "y": -0.000457763671875,
        "z": 0.0018310546875,
        "roll": -0.0002619326114654541,
        "pitch": 0.0029244422912597656,
        "yaw": -9.062886238098145e-05,
        "gripper": 0.0008544921875
      },
      "compiled_p50_seconds": 0.08497201278805733,
      "eager_p50_seconds": 0.12593493983149529,
      "time_ratio_p50": 0.6776904244793911
    },
    {
      "target": "action_head_dit_attn_all",
      "case": "task6:init8",
      "policy_step": 248,
      "samples": 15,
      "continuous_max_abs_max": 0.00091552734375,
      "continuous_max_abs_p99": 0.00091552734375,
      "continuous_l2_p99": 0.0010449393089765199,
      "same_seed_repeat_span_max": 0.0,
      "top_dim": "z",
      "top_seed_offset": -2,
      "top_repeat": 0,
      "raw_diff": {
        "x": 0.0004863739013671875,
        "y": 0.0,
        "z": -0.00091552734375,
        "roll": 0.0001309514045715332,
        "pitch": 0.0,
        "yaw": 0.0,
        "gripper": -0.0003662109375
      },
      "compiled_p50_seconds": 0.10176411271095276,
      "eager_p50_seconds": 0.11181725561618805,
      "time_ratio_p50": 0.913191460872895
    },
    {
      "target": "action_head_dit_attn_all",
      "case": "task6:init8",
      "policy_step": 249,
      "samples": 15,
      "continuous_max_abs_max": 0.0010013580322265625,
      "continuous_max_abs_p99": 0.0010013580322265625,
      "continuous_l2_p99": 0.0011363190797349493,
      "same_seed_repeat_span_max": 0.0,
      "top_dim": "z",
      "top_seed_offset": 2,
      "top_repeat": 0,
      "raw_diff": {
        "x": -0.00036835670471191406,
        "y": 0.0,
        "z": -0.0010013580322265625,
        "roll": 0.0,
        "pitch": 0.0001462101936340332,
        "yaw": 0.0003625452518463135,
        "gripper": 0.00048828125
      },
      "compiled_p50_seconds": 0.10286158323287964,
      "eager_p50_seconds": 0.10628240182995796,
      "time_ratio_p50": 0.9452867797270882
    },
    {
      "target": "action_head_dit_attn_all",
      "case": "task6:init8",
      "policy_step": 250,
      "samples": 15,
      "continuous_max_abs_max": 0.00091552734375,
      "continuous_max_abs_p99": 0.00091552734375,
      "continuous_l2_p99": 0.0010311365168951762,
      "same_seed_repeat_span_max": 0.0,
      "top_dim": "y",
      "top_seed_offset": 2,
      "top_repeat": 0,
      "raw_diff": {
        "x": 0.0,
        "y": 0.00091552734375,
        "z": 0.000457763671875,
        "roll": 9.82135534286499e-05,
        "pitch": 7.31050968170166e-05,
        "yaw": 2.2679567337036133e-05,
        "gripper": 0.0
      },
      "compiled_p50_seconds": 0.09713691100478172,
      "eager_p50_seconds": 0.10780300199985504,
      "time_ratio_p50": 0.8998639997534894
    },
    {
      "target": "action_head_dit_attn_all",
      "case": "task6:init8",
      "policy_step": 251,
      "samples": 15,
      "continuous_max_abs_max": 0.00091552734375,
      "continuous_max_abs_p99": 0.00091552734375,
      "continuous_l2_p99": 0.0009720184155533844,
      "same_seed_repeat_span_max": 0.0,
      "top_dim": "z",
      "top_seed_offset": -2,
      "top_repeat": 0,
      "raw_diff": {
        "x": 0.0,
        "y": 0.0002288818359375,
        "z": -0.00091552734375,
        "roll": 0.0,
        "pitch": -0.0001462101936340332,
        "yaw": -0.00018128752708435059,
        "gripper": 0.0
      },
      "compiled_p50_seconds": 0.10486995801329613,
      "eager_p50_seconds": 0.10380755364894867,
      "time_ratio_p50": 1.0489203566030796
    },
    {
      "target": "action_head_dit_attn_all",
      "case": "task6:init8",
      "policy_step": 252,
      "samples": 15,
      "continuous_max_abs_max": 0.00091552734375,
      "continuous_max_abs_p99": 0.00091552734375,
      "continuous_l2_p99": 0.0009446809517833604,
      "same_seed_repeat_span_max": 0.0,
      "top_dim": "y",
      "top_seed_offset": -2,
      "top_repeat": 0,
      "raw_diff": {
        "x": 0.0,
        "y": 0.00091552734375,
        "z": 0.0,
        "roll": 0.0,
        "pitch": 0.0001462101936340332,
        "yaw": -0.0001812577247619629,
        "gripper": 0.0
      },
      "compiled_p50_seconds": 0.10645811632275581,
      "eager_p50_seconds": 0.10739854350686073,
      "time_ratio_p50": 1.0136400352902013
    },
    {
      "target": "action_head_dit_attn_all",
      "case": "task6:init8",
      "policy_step": 253,
      "samples": 15,
      "continuous_max_abs_max": 0.0018310546875,
      "continuous_max_abs_p99": 0.0018310546875,
      "continuous_l2_p99": 0.0025421143565768534,
      "same_seed_repeat_span_max": 0.0,
      "top_dim": "x",
      "top_seed_offset": 0,
      "top_repeat": 0,
      "raw_diff": {
        "x": 0.0018310546875,
        "y": 0.0003147125244140625,
        "z": 0.0016021728515625,
        "roll": -0.0002619326114654541,
        "pitch": -0.0005849003791809082,
        "yaw": -0.00018128752708435059,
        "gripper": 0.0
      },
      "compiled_p50_seconds": 0.10469267144799232,
      "eager_p50_seconds": 0.1078391782939434,
      "time_ratio_p50": 0.9698846485590501
    },
    {
      "target": "action_head_dit_attn_all",
      "case": "task6:init8",
      "policy_step": 254,
      "samples": 15,
      "continuous_max_abs_max": 0.001373291015625,
      "continuous_max_abs_p99": 0.001373291015625,
      "continuous_l2_p99": 0.0014534882063925061,
      "same_seed_repeat_span_max": 0.0,
      "top_dim": "y",
      "top_seed_offset": -2,
      "top_repeat": 0,
      "raw_diff": {
        "x": 0.0,
        "y": 0.001373291015625,
        "z": 0.000457763671875,
        "roll": -0.00013096630573272705,
        "pitch": 0.0,
        "yaw": 0.0,
        "gripper": -0.00048828125
      },
      "compiled_p50_seconds": 0.10378806293010712,
      "eager_p50_seconds": 0.10636668652296066,
      "time_ratio_p50": 0.9723903163673057
    },
    {
      "target": "action_head_dit_attn_all",
      "case": "task6:init8",
      "policy_step": 255,
      "samples": 15,
      "continuous_max_abs_max": 0.00125885009765625,
      "continuous_max_abs_p99": 0.00125885009765625,
      "continuous_l2_p99": 0.0016863489509489574,
      "same_seed_repeat_span_max": 0.0,
      "top_dim": "z",
      "top_seed_offset": -1,
      "top_repeat": 0,
      "raw_diff": {
        "x": -0.0007197856903076172,
        "y": -0.000858306884765625,
        "z": -0.00125885009765625,
        "roll": -6.54757022857666e-05,
        "pitch": 0.0,
        "yaw": 0.0,
        "gripper": 0.0
      },
      "compiled_p50_seconds": 0.10381600260734558,
      "eager_p50_seconds": 0.10651971772313118,
      "time_ratio_p50": 0.971625378980953
    },
    {
      "target": "action_head_dit_attn_all",
      "case": "task6:init8",
      "policy_step": 256,
      "samples": 15,
      "continuous_max_abs_max": 0.00091552734375,
      "continuous_max_abs_p99": 0.00091552734375,
      "continuous_l2_p99": 0.0009821010406916913,
      "same_seed_repeat_span_max": 0.0,
      "top_dim": "y",
      "top_seed_offset": 1,
      "top_repeat": 0,
      "raw_diff": {
        "x": 0.0,
        "y": -0.00091552734375,
        "z": 0.0002288818359375,
        "roll": -0.00026191771030426025,
        "pitch": 7.31050968170166e-05,
        "yaw": 0.0,
        "gripper": -0.00048828125
      },
      "compiled_p50_seconds": 0.09951441362500191,
      "eager_p50_seconds": 0.11163840815424919,
      "time_ratio_p50": 0.9110028985252396
    },
    {
      "target": "action_head_dit_attn_all",
      "case": "task6:init8",
      "policy_step": 257,
      "samples": 15,
      "continuous_max_abs_max": 0.0008773207664489746,
      "continuous_max_abs_p99": 0.0008773207664489746,
      "continuous_l2_p99": 0.0008935179637356515,
      "same_seed_repeat_span_max": 0.0,
      "top_dim": "pitch",
      "top_seed_offset": 2,
      "top_repeat": 0,
      "raw_diff": {
        "x": 0.0001430511474609375,
        "y": 0.0,
        "z": 0.0,
        "roll": 0.0,
        "pitch": -0.0008773207664489746,
        "yaw": 9.065866470336914e-05,
        "gripper": -0.0001220703125
      },
      "compiled_p50_seconds": 0.10367081314325333,
      "eager_p50_seconds": 0.1067296676337719,
      "time_ratio_p50": 0.971845965001556
    },
    {
      "target": "action_head_dit_attn_all",
      "case": "task6:init8",
      "policy_step": 258,
      "samples": 15,
      "continuous_max_abs_max": 0.0019598007202148438,
      "continuous_max_abs_p99": 0.0019598007202148438,
      "continuous_l2_p99": 0.0029791698494895467,
      "same_seed_repeat_span_max": 0.0,
      "top_dim": "x",
      "top_seed_offset": 1,
      "top_repeat": 0,
      "raw_diff": {
        "x": -0.0019598007202148438,
        "y": 0.00091552734375,
        "z": -0.0018310546875,
        "roll": 0.0,
        "pitch": -0.0008773505687713623,
        "yaw": 0.00027191638946533203,
        "gripper": -0.0001220703125
      },
      "compiled_p50_seconds": 0.10403793305158615,
      "eager_p50_seconds": 0.10676223412156105,
      "time_ratio_p50": 0.9744825397071312
    }
  ]
}